fastlog/__init__.py
fastlog/hexdump.py
fastlog/log.py
fastlog/term.py
fastlog/termcap.py
fastlog/styles/__init__.py
fastlog/styles/pwntools.py
fastlog-1.0.0b3.dist-info/LICENSE.txt
fastlog-1.0.0b3.dist-info/METADATA
fastlog-1.0.0b3.dist-info/WHEEL
fastlog-1.0.0b3.dist-info/top_level.txt
fastlog-1.0.0b3.dist-info/RECORD
